{
  "color": "GREEN",
  "cost": 1,
  "flavor": "了解！",
  "image": "https://s3-ap-northeast-1.amazonaws.com/static.ws-tcg.com/wordpress/wp-content/cardimages/t/tf_s32/tf_s32_035.gif",
  "level": 1,
  "name": "“アネックス1号の乗組員”三条 加奈子",
  "power": 6500,
  "rarity": "U",
  "side": "S",
  "soul": 1,
  "text": "【起】［手札の《改造》のキャラを1枚控え室に置く］ あなたは自分の山札の上から1枚を公開する。そのカードが《改造》のキャラなら、そのターン中、このカードは次の能力を得る。『【永】 このカードがアタックする時、あなたはかわりに相手の後列のキャラを1枚選び、このカードはそのキャラを防御キャラとしてフロントアタックしてよい。』（公開したカードは元に戻す）",
  "trait": [
    "改造",
    "動物"
  ],
  "trigger": [
  ],
  "type": "Character"
}