{
  "color": "BLUE",
  "cost": 0,
  "flavor": "私はキミを願って魔法少女になったんだ",
  "image": "https://s3-ap-northeast-1.amazonaws.com/static.ws-tcg.com/wordpress/wp-content/cardimages/m/mr_w59/mr_w59_085.gif",
  "level": 0,
  "name": "織莉子への忠誠心 キリカ",
  "power": 2000,
  "rarity": "U",
  "side": "W",
  "soul": 1,
  "text": "【永】 このカードの下にマーカーがあるなら、このカードのレベルを＋1し、パワーを＋1500。\n【自】 このカードが手札から舞台に置かれた時、あなたは自分の山札の上から1枚を公開する。そのカードが《魔法》のキャラならこのカードの下にマーカーとして裏向きに置いてよい。（そうしないなら元に戻す）",
  "trait": [
    "魔法",
    "ディフェンス"
  ],
  "trigger": [
  ],
  "type": "Character"
}