{
  "color": "YELLOW",
  "cost": 0,
  "flavor": "響「今日の夜更かしに備えてお昼寝するなら、ちょっと疲れたくらいが良くないかな？」",
  "image": "https://s3-ap-northeast-1.amazonaws.com/static.ws-tcg.com/wordpress/wp-content/cardimages/s/sg_w39/sg_w39_010.gif",
  "level": 1,
  "name": "お昼寝の準備 響＆未来",
  "power": 500,
  "rarity": "U",
  "side": "W",
  "soul": 1,
  "text": "【永】 他のあなたの《音楽》のキャラすべてに、パワーを＋500。\n【自】 このカードが手札から舞台に置かれた時、あなたは自分の山札を上から2枚まで見て、カードを1枚まで選び、手札に加え、残りのカードを控え室に置く。あなたは自分の手札を1枚選び、控え室に置く。",
  "trait": [
    "音楽",
    "-"
  ],
  "trigger": [
  ],
  "type": "Character"
}