{
  "color": "YELLOW",
  "cost": 0,
  "flavor": "あたしに投票してくださった隊長さん\n本当にありがとうございます！",
  "image": "https://s3-ap-northeast-1.amazonaws.com/static.ws-tcg.com/wordpress/wp-content/cardimages/s/sgs_s37/sgs_s37_007.gif",
  "level": 0,
  "name": "二代目エテルノクイーン 伊緒",
  "power": 500,
  "rarity": "R",
  "side": "S",
  "soul": 1,
  "text": "【自】 このカードの与えたダメージがキャンセルされた時、あなたはこのカードをストック置場に置いてよい。\n【自】 このカードが【リバース】した時、このカードのバトル相手のレベルが0以下なら、あなたはそのキャラをストック置場に置いてよい。そうしたら、あなたは相手のストックの下から1枚を、控え室に置く。",
  "trait": [
    "ストライカー",
    "クイーン"
  ],
  "trigger": [
  ],
  "type": "Character"
}