{
  "color": "GREEN",
  "cost": 1,
  "flavor": "ウチはまだまだイケるよ？",
  "image": "https://s3-ap-northeast-1.amazonaws.com/static.ws-tcg.com/wordpress/wp-content/cardimages/l/ll_w28/ll_w28_040.gif",
  "level": 2,
  "name": "レッスン着の希",
  "power": 7500,
  "rarity": "R",
  "side": "W",
  "soul": 1,
  "text": "【自】 このカードが手札から舞台に置かれた時、そのターン中、このカードのパワーを＋1500。\n【自】 アンコール ［あなたの山札の上から1枚をクロック置場に置く］ （このカードが舞台から控え室に置かれた時、あなたはコストを払ってよい。そうしたら、このカードがいた枠に【レスト】して置く）",
  "trait": [
    "音楽",
    "占い"
  ],
  "trigger": [
    "SOUL"
  ],
  "type": "Character"
}