{
  "color": "YELLOW",
  "cost": 1,
  "flavor": "大丈夫、炎なら少しは防げます！！",
  "image": "https://s3-ap-northeast-1.amazonaws.com/static.ws-tcg.com/wordpress/wp-content/cardimages/r/rw_w15/rw_w15_008.gif",
  "level": 2,
  "name": "“守りの包帯”ちはや",
  "power": 5000,
  "rarity": "R",
  "side": "W",
  "soul": 1,
  "text": "【永】 応援 このカードの前のあなたのキャラすべてに、パワーを＋Ｘ。Ｘはそのキャラのレベル×500に等しい。\n【自】【クロック】 シフト レベル2 （あなたのメインフェイズの始めに、あなたは自分の手札の黄のカードを1枚とクロック置場のこのカードを選び、入れ替えてよい）",
  "trait": [
    "お菓子",
    "マスター"
  ],
  "trigger": [
    "SOUL"
  ],
  "type": "Character"
}