{
  "color": "RED",
  "cost": 2,
  "image": "https://s3-ap-northeast-1.amazonaws.com/static.ws-tcg.com/wordpress/wp-content/cardimages/k/kg_se07/kg_se07_33.gif",
  "level": 3,
  "name": "鑢 七実",
  "power": 10000,
  "rarity": "R",
  "side": "S",
  "soul": 2,
  "text": "【自】 このカードが手札から舞台に置かれた時、あなたは自分の控え室の《武器》のキャラを1枚選び、手札に戻してよい。\n【自】［(4)］ このカードがアタックした時、クライマックス置場に「対決 七実対七花」があるなら、あなたはコストを払ってよい。そうしたら、あなたは相手の前列のレベル2以下のキャラすべてを、控え室に置く。\n【自】 あなたのドローフェイズの始めに、あなたは自分のストックの上から1枚を、控え室に置く。そうしたら、そのターン中、このカードのパワーを＋2500。",
  "trait": [
    "武器",
    "和服"
  ],
  "trigger": [
    "SOUL"
  ],
  "type": "Character"
}