{
  "color": "YELLOW",
  "cost": 2,
  "flavor": "あ、あはは。いつもと違う格好だから、ちょっと転んじゃった",
  "image": "https://s3-ap-northeast-1.amazonaws.com/static.ws-tcg.com/wordpress/wp-content/cardimages/d/dc_w01/dc_w01_010.gif",
  "level": 2,
  "name": "巫女装束の音姫",
  "power": 8000,
  "rarity": "U",
  "side": "W",
  "soul": 2,
  "text": "【自】 このカードがアタックした時、クライマックス置場に「存在のなくなる日」があるなら、あなたは相手のキャラを1枚選び、手札に戻してよい。\n【起】［(1)］ そのターン中、このカードのソウルを＋1。",
  "trait": [
    "魔法",
    "巫女"
  ],
  "trigger": [
    "SOUL"
  ],
  "type": "Character"
}