{
  "color": "RED",
  "cost": 0,
  "flavor": "いい加減に起きないとダメだよ！",
  "image": "https://s3-ap-northeast-1.amazonaws.com/static.ws-tcg.com/wordpress/wp-content/cardimages/n/nm_s24/nm_s24_062.gif",
  "level": 1,
  "name": "朝の光景 阿良々木月火",
  "power": 2000,
  "rarity": "C",
  "side": "S",
  "soul": 1,
  "text": "【自】 あなたがこのカードの『助太刀』を使った時、あなたは自分のバトル中の赤のキャラを1枚選び、そのターン中、パワーを＋1000。\n【起】【カウンター】 助太刀1000 レベル1 ［手札のこのカードを控え室に置く］ （あなたは自分のフロントアタックされているキャラを1枚選び、そのターン中、パワーを＋1000）",
  "trait": [
    "怪異",
    "和服"
  ],
  "trigger": [
  ],
  "type": "Character"
}