{
  "color": "RED",
  "cost": 0,
  "flavor": "翼が一緒に唄ってくれるってんなら、\nこれ以上、心強いものはないな",
  "image": "https://s3-ap-northeast-1.amazonaws.com/static.ws-tcg.com/wordpress/wp-content/cardimages/s/sg_w52/sg_w52_065.gif",
  "level": 1,
  "name": "片翼の装者 奏",
  "power": 5500,
  "rarity": "U",
  "side": "W",
  "soul": 1,
  "text": "【永】 経験 あなたのレベル置場に「【蒼ノ一閃 滅破：心】翼」があるなら、このカードのパワーを＋1500。\n【自】 バトル中のこのカードが【リバース】した時、そのターン中、あなたは『【自】 アンコール』を使えない。（ルールによる『【自】 アンコール ［(3)］』も使えない）",
  "trait": [
    "音楽",
    "武器"
  ],
  "trigger": [
  ],
  "type": "Character"
}