{
  "color": "RED",
  "cost": 0,
  "flavor": "私たちが築く、新しい大怪盗時代のアイコンとして、あなたはまだ必要なの",
  "image": "https://s3-ap-northeast-1.amazonaws.com/static.ws-tcg.com/wordpress/wp-content/cardimages/m/mk_s33/mk_s33_058.gif",
  "level": 0,
  "name": "何かを企む十津川",
  "power": 1000,
  "rarity": "U",
  "side": "S",
  "soul": 1,
  "text": "【永】 舞台にこのカードがいるなら、このカードは《怪盗》を得る。\n【永】 他のあなたの、《警察》か《怪盗》のキャラすべてに、パワーを＋500。\n【自】 チェンジ ［このカードを控え室に置く］ あなたのドローフェイズの始めに、あなたはコストを払ってよい。そうしたら、あなたは自分の控え室の「桃怪盗“麗しき破滅の桃”」を1枚選び、このカードがいた枠に置く。",
  "trait": [
    "警察",
    "-"
  ],
  "trigger": [
  ],
  "type": "Character"
}