{
  "color": "RED",
  "cost": 0,
  "flavor": "可能性はある。",
  "image": "https://s3-ap-northeast-1.amazonaws.com/static.ws-tcg.com/wordpress/wp-content/cardimages/l/lb_w02/lb_w02_055.gif",
  "level": 1,
  "name": "直枝 理樹",
  "power": 4500,
  "rarity": "R",
  "side": "W",
  "soul": 1,
  "text": "【自】［(1)］ このカードがアタックした時、クライマックス置場に「リトルバスターズ！」があるなら、あなたはコストを払ってよい。そうしたら、自分の控え室のキャラを1枚選び、手札に戻す。\n【自】 アンコール ［手札のキャラを1枚控え室に置く］ （このカードが舞台から控え室に置かれた時、あなたはコストを払ってよい。そうしたら、このカードがいた枠に【レスト】して置く）",
  "trait": [
    "スポーツ",
    "-"
  ],
  "trigger": [
  ],
  "type": "Character"
}