{
  "color": "YELLOW",
  "cost": 2,
  "flavor": "だってあたしは、ありがとうをあなたに言いに来たんだから",
  "image": "https://s3-ap-northeast-1.amazonaws.com/static.ws-tcg.com/wordpress/wp-content/cardimages/a/ab_w31/ab_w31_012.gif",
  "level": 3,
  "name": "結弦の心臓 かなで",
  "power": 10000,
  "rarity": "R",
  "side": "W",
  "soul": 2,
  "text": "【自】 このカードが手札から舞台に置かれた時、あなたは自分のクロックの上から1枚を、控え室に置いてよい。\n【自】 このカードのバトル相手が【リバース】した時、あなたはそのキャラを思い出にしてよい。",
  "trait": [
    "死",
    "生徒会"
  ],
  "trigger": [
    "SOUL"
  ],
  "type": "Character"
}