{
  "color": "RED",
  "cost": 2,
  "flavor": "へ……それ、喜べばいいの…？怒ればいいの…？",
  "image": "https://s3-ap-northeast-1.amazonaws.com/static.ws-tcg.com/wordpress/wp-content/cardimages/a/ab_w31/ab_w31_113.gif",
  "level": 3,
  "name": "仲村 ゆり",
  "power": 9500,
  "rarity": "RR",
  "side": "W",
  "soul": 2,
  "text": "【自】 このカードが手札から舞台に置かれた時、あなたは2枚まで引き、自分の手札を1枚選び、控え室に置く。\n【自】 このカードがアタックした時、クライマックス置場に「世界の核心」があるなら、相手に1ダメージを与え、次の相手のターンの終わりまで、このカードのパワーを＋1500。（ダメージキャンセルは発生する）",
  "trait": [
    "死",
    "武器"
  ],
  "trigger": [
    "SOUL"
  ],
  "type": "Character"
}